dj_settings/__init__.py
dj_settings/_seven.py
dj_settings/_seven.pyi
dj_settings/constants.py
dj_settings/exceptions.py
dj_settings/py.typed
dj_settings/settings.py
dj_settings/type_defs.py
dj_settings/utils.py
dj_settings-8.0.0.dist-info/LICENSE.md
dj_settings-8.0.0.dist-info/METADATA
dj_settings-8.0.0.dist-info/WHEEL
dj_settings-8.0.0.dist-info/RECORD
