Metadata-Version: 2.3
Name: dj-settings
Version: 8.0.0
Summary: project settings the UNIX way
Home-page: https://dj-settings.readthedocs.io/en/stable/
License: BSD-3-Clause
Keywords: configuration,settings
Author: Stephanos Kuma
Author-email: "Stephanos Kuma" <stephanos@kuma.ai>
Requires-Python: >=3.9
Classifier: Development Status :: 5 - Production/Stable
Classifier: Intended Audience :: Developers
Classifier: License :: OSI Approved :: BSD License
Classifier: Operating System :: OS Independent
Classifier: Programming Language :: Python :: 3 :: Only
Requires-Dist: pyutilkit (~=0.10)
Requires-Dist: ruamel-yaml (~=0.18)
Requires-Dist: tomli (~=2.0) ; python_version < '3.11'
Project-URL: Documentation, https://dj-settings.readthedocs.io/en/stable/
Project-URL: Repository, https://github.com/spapanik/dj_settings
